[
    {
        "id": 1,
        "name": "Carlos Ramirez",
        "phone": "(301) 391-6950",
        "email": "carlos@email.com",
        "DOB": "03/17/1993"
    },
    {
        "id": 2,
        "name": "Ben Con",
        "phone": "(401) 478-3254",
        "email": "ben@email.com",
        "DOB": "04/16/1991"
    },
    {
        "id": 3,
        "name": "Sean Penn",
        "phone": "(240) 548-6454",
        "email": "sean@eamil.com",
        "DOB": "09/10/1989"
    },
    {
        "id": 4,
        "name": "Jon Con",
        "phone": "(401) 564-4586",
        "email": "Jon@eamil.com",
        "DOB": "10/20/1990"
    },
    {
        "id": 5,
        "name": "Kelly Bean",
        "phone": "(456) 478-3544",
        "email": "kelly@eamil.com",
        "DOB": "04/16/1991"
    },
    {
        "id": 6,
        "name": "Ben Con",
        "phone": "(401) 478-3254",
        "email": "ben@eamil.com",
        "DOB": "04/16/1991"
    },
    {
        "id": 7,
        "name": "Ben Con",
        "phone": "(401) 478-3254",
        "email": "ben@eamil.com",
        "DOB": "04/16/1991"
    },
    {
        "id": 8,
        "name": "Ben Con",
        "phone": "(401) 478-3254",
        "email": "ben@eamil.com",
        "DOB": "04/16/1991"
    },
    {
        "id": 9,
        "name": "Ben Con",
        "phone": "(401) 478-3254",
        "email": "ben@eamil.com",
        "DOB": "04/16/1991"
    },
    {
        "id": 10,
        "name": "Ben Con",
        "phone": "(401) 478-3254",
        "email": "ben@eamil.com",
        "DOB": "04/16/1991"
    }
]